pyplater/__init__.py
pyplater/tag.py
pyplater/utils.py
pyplater-0.1.0.dist-info/LICENSE
pyplater-0.1.0.dist-info/METADATA
pyplater-0.1.0.dist-info/WHEEL
pyplater-0.1.0.dist-info/top_level.txt
pyplater-0.1.0.dist-info/zip-safe
pyplater-0.1.0.dist-info/RECORD
