Metadata-Version: 2.1
Name: pyplater
Version: 0.1.0
Summary: Build html component with python
Home-page: https://github.com/Unviray/pyplater
Author: Unviray
Author-email: unviray@gmail.com
License: MIT license
Keywords: html component react angular vue javascript js nodejs node
Platform: UNKNOWN
Classifier: Development Status :: 2 - Pre-Alpha
Classifier: Intended Audience :: Developers
Classifier: License :: OSI Approved :: MIT License
Classifier: Programming Language :: Python :: 3.6
Classifier: Programming Language :: Python :: 3.7
Requires-Python: >=3.6
